python_color/__init__.py
python_color/color.py
example_package_yifei_chen-0.0.2.dist-info/LICENSE
example_package_yifei_chen-0.0.2.dist-info/METADATA
example_package_yifei_chen-0.0.2.dist-info/WHEEL
example_package_yifei_chen-0.0.2.dist-info/top_level.txt
example_package_yifei_chen-0.0.2.dist-info/RECORD
