Metadata-Version: 2.1
Name: example_package_yifei_chen
Version: 0.0.2
Summary: red green
Author-email: yifei_chen <18501930842@163.com>
Project-URL: Homepage, https://github.com/pypa/sampleproject
Project-URL: Bug Tracker, https://github.com/pypa/sampleproject/issues
Classifier: Programming Language :: Python :: 3
Classifier: License :: OSI Approved :: MIT License
Classifier: Operating System :: OS Independent
Requires-Python: >=3.7
License-File: LICENSE
